MoleculeSculptor/__init__.py
MoleculeSculptor/src/__init__.py
MoleculeSculptor/src/functional_group.csv
MoleculeSculptor/src/sculptor.py
MoleculeSculptor/src/subgroup.py
MoleculeSculptor/src/utils.py
MoleculeSculptor-1.0.1.dist-info/METADATA
MoleculeSculptor-1.0.1.dist-info/WHEEL
MoleculeSculptor-1.0.1.dist-info/top_level.txt
MoleculeSculptor-1.0.1.dist-info/RECORD
