Metadata-Version: 2.1
Name: MoleculeSculptor
Version: 1.0.1
Summary: Molecule Segmentation Tool
Home-page: https://github.com/ACCA-KU/MoleculeSculptor
Author: Park Jinyong
Author-email: phillip1998@korea.ac.kr
Classifier: Programming Language :: Python :: 3
Classifier: License :: OSI Approved :: MIT License
Classifier: Operating System :: OS Independent
Requires-Python: >=3.8
Requires-Dist: pandas
Requires-Dist: numpy
Requires-Dist: matplotlib
Requires-Dist: rdkit
